{
  "date": "2026-04-09 12:05",
  "all_games_today": [
    {
      "away_team": "Hawks",
      "home_team": "Cavaliers",
      "away_score": 116,
      "home_score": 122,
      "score": "116 - 122",
      "status": "Final",
      "quarter": 4,
      "time_remaining": "",
      "is_live": true,
      "is_completed": false
    },
    {
      "away_team": "Timberwolves",
      "home_team": "Magic",
      "away_score": 120,
      "home_score": 132,
      "score": "120 - 132",
      "status": "Final",
      "quarter": 4,
      "time_remaining": "",
      "is_live": true,
      "is_completed": false
    },
    {
      "away_team": "Bucks",
      "home_team": "Pistons",
      "away_score": 111,
      "home_score": 137,
      "score": "111 - 137",
      "status": "Final",
      "quarter": 4,
      "time_remaining": "",
      "is_live": true,
      "is_completed": false
    },
    {
      "away_team": "Grizzlies",
      "home_team": "Nuggets",
      "away_score": 119,
      "home_score": 136,
      "score": "119 - 136",
      "status": "Final",
      "quarter": 4,
      "time_remaining": "",
      "is_live": true,
      "is_completed": false
    },
    {
      "away_team": "Trail Blazers",
      "home_team": "Spurs",
      "away_score": 101,
      "home_score": 112,
      "score": "101 - 112",
      "status": "Final",
      "quarter": 4,
      "time_remaining": "",
      "is_live": true,
      "is_completed": false
    },
    {
      "away_team": "Thunder",
      "home_team": "Clippers",
      "away_score": 128,
      "home_score": 110,
      "score": "128 - 110",
      "status": "Final",
      "quarter": 4,
      "time_remaining": "",
      "is_live": true,
      "is_completed": false
    },
    {
      "away_team": "Mavericks",
      "home_team": "Suns",
      "away_score": 107,
      "home_score": 112,
      "score": "107 - 112",
      "status": "Final",
      "quarter": 4,
      "time_remaining": "",
      "is_live": true,
      "is_completed": false
    }
  ]
}