{
  "date": "2026-04-04 20:50",
  "all_games_today": [
    {
      "away_team": "Wizards",
      "home_team": "Heat",
      "away_score": 91,
      "home_score": 120,
      "score": "91 - 120",
      "status": "Q3 :05.2",
      "quarter": 3,
      "time_remaining": "PT00M05.20S",
      "is_live": true,
      "is_completed": false
    },
    {
      "away_team": "Spurs",
      "home_team": "Nuggets",
      "away_score": 85,
      "home_score": 82,
      "score": "85 - 82",
      "status": "Q3 6:28",
      "quarter": 3,
      "time_remaining": "PT06M28.00S",
      "is_live": true,
      "is_completed": false
    },
    {
      "away_team": "Pistons",
      "home_team": "76ers",
      "away_score": 0,
      "home_score": 0,
      "score": "N/A",
      "status": "7:00 pm ET",
      "quarter": 0,
      "time_remaining": "",
      "is_live": false,
      "is_completed": false
    }
  ]
}